Workbook
Name Slicer_Category: #N/A
Name Slicer_Region: #N/A
Name Slicer_Years__Date: #N/A

Sheet Project Instructions
A1: PR. Final Project - "Data Intelligence Dashboard"
A2: Dataset: Use the 'Final Project Dataset' sheet containing 200+ records of customer transactions. Objective: Create a full-fledged analysis and reporting solution using Excel to analyze customer transactions, find insights, and build visualizations and dashboards. Key Topics to Implement: - Date & Time Functions: TODAY, NOW, DATEDIF, EOMONTH - FILTER Function for multi-value returns - Conditional Formatting with Icons/Arrows - Create Timestamp (using NOW and iterative calculations) - WHAT-IF Analysis: Scenario Manager, Goal Seek - Linear Regression using Data Analysis Toolpak - Data Analysis & Storytelling from the dataset - Use GroupBy concepts to find High-Value Customers using formulas - Create Dashboard using: - Pivot Tables - Pivot Charts (Bar, Line, Pie) - Slicers and Timelines - KPI Indicators with Conditional Formatting - Find most frequently purchased product or repeating names using formulas - Compare two lists and extract matching names in a new column - Create Abbreviations using TEXT functions - Build a final report with insights and storytelling Deliverable: - Well-structured workbook with multiple sheets (Raw Data, Analysis, Visualizations, Dashboard) - Summary Insights with key metrics: Total Revenue, Top Customers, Most Sold Products, Regional Sales - Use of all required formulas and functions as listed above

Sheet Sheet1
A3: Sum of Total_Amount | B3: Column Labels
A4: Row Labels | B4: Appliances | C4: Electronics | D4: Furniture | E4: Grand Total
A5: 2024
A6: Qtr2 | B6: 2439.62 | C6: 45118.99 | D6: 9699.52 | E6: 57258.13
A7: Qtr3 | B7: 1939.72 | C7: 34589.12 | D7: 10699.5 | E7: 47228.34
A8: Qtr4 | B8: 1519.77 | C8: 42939.04 | D8: 11499.45 | E8: 55958.26
A9: 2025
A10: Qtr1 | B10: 2199.66 | C10: 42369.04 | D10: 17199.21 | E10: 61767.91
A11: Qtr2 | B11: 239.97 | C11: 6739.86 | E11: 6979.83
A12: Grand Total | B12: 8338.74 | C12: 171756.05 | D12: 49097.68 | E12: 229192.47
A32: Sum of Quantity | B32: Column Labels
A33: Row Labels | B33: Appliances | C33: Electronics | D33: Furniture | E33: Grand Total
A34: 2024 | B34: 89 | C34: 285 | D34: 153 | E34: 527
A35: 2025 | B35: 37 | C35: 110 | D35: 79 | E35: 226
A36: Grand Total | B36: 126 | C36: 395 | D36: 232 | E36: 753

Sheet Dashboard
A1: dashboard
L17: =GETPIVOTDATA("Total_Amount",Sheet1!$A$3) -> 229192.47
P19: =GETPIVOTDATA("Quantity",Sheet1!$A$32) -> 753
L22: =Sheet1!$B$4 -> Appliances

Sheet Raw data
A1: Transaction_ID | B1: Date | C1: Customer_ID | D1: Customer_Name | E1: Product_ID | F1: Product_Name | G1: Category | H1: Quantity | I1: Unit_Price | J1: Payment_Method | K1: Region | L1: Customer_Segment | M1: Customer_Since | N1: Total_Amount
A2: TRX0230 | B2: 45409 | C2: CUST027 | D2: George Adams | E2: P001 | F2: Laptop | G2: Electronics | H2: 1 | I2: 899.99 | J2: Debit Card | K2: North | L2: Standard | M2: 44920 | N2: 899.99
A3: TRX0041 | B3: 45432 | C3: CUST021 | D3: Kevin Scott | E3: P001 | F3: Laptop | G3: Electronics | H3: 1 | I3: 899.99 | J3: Credit Card | K3: West | L3: Premium | M3: 44578 | N3: 899.99
A4: TRX0042 | B4: 45443 | C4: CUST019 | D4: Daniel King | E4: P004 | F4: Coffee Maker | G4: Appliances | H4: 1 | I4: 79.99 | J4: Cash | K4: North | L4: Standard | M4: 44917 | N4: 79.99
A5: TRX0061 | B5: 45460 | C5: CUST028 | D5: Betty Campbell | E5: P005 | F5: Blender | G5: Appliances | H5: 1 | I5: 59.99 | J5: Debit Card | K5: West | L5: Premium | M5: 45190 | N5: 59.99
A6: TRX0117 | B6: 45444 | C6: CUST017 | D6: Charles Allen | E6: P010 | F6: Keyboard | G6: Electronics | H6: 1 | I6: 89.99 | J6: Cash | K6: North | L6: Basic | M6: 45141 | N6: 89.99
A7: TRX0121 | B7: 45449 | C7: CUST028 | D7: Betty Campbell | E7: P010 | F7: Keyboard | G7: Electronics | H7: 1 | I7: 89.99 | J7: Credit Card | K7: South | L7: Standard | M7: 44582 | N7: 89.99
A8: TRX0192 | B8: 45475 | C8: CUST017 | D8: Charles Allen | E8: P010 | F8: Keyboard | G8: Electronics | H8: 1 | I8: 89.99 | J8: PayPal | K8: West | L8: Standard | M8: 44802 | N8: 89.99
A9: TRX0052 | B9: 45476 | C9: CUST022 | D9: Susan Green | E9: P010 | F9: Keyboard | G9: Electronics | H9: 1 | I9: 89.99 | J9: Cash | K9: South | L9: Standard | M9: 44611 | N9: 89.99
A10: TRX0018 | B10: 45484 | C10: CUST013 | D10: Joseph Jackson | E10: P003 | F10: Headphones | G10: Electronics | H10: 1 | I10: 149.99 | J10: Cash | K10: Central | L10: Standard | M10: 44909 | N10: 149.99
A11: TRX0162 | B11: 45496 | C11: CUST040 | D11: Sharon Butler | E11: P001 | F11: Laptop | G11: Electronics | H11: 1 | I11: 899.99 | J11: Cash | K11: Central | L11: Standard | M11: 45179 | N11: 899.99
A12: TRX0078 | B12: 45469 | C12: CUST021 | D12: Kevin Scott | E12: P004 | F12: Coffee Maker | G12: Appliances | H12: 1 | I12: 79.99 | J12: PayPal | K12: Central | L12: Premium | M12: 45352 | N12: 79.99
A13: TRX0138 | B13: 45408 | C13: CUST022 | D13: Susan Green | E13: P008 | F13: Bookshelf | G13: Furniture | H13: 1 | I13: 149.99 | J13: Credit Card | K13: West | L13: Standard | M13: 45103 | N13: 149.99
... A251: TRX0213 | B251: 45745 | C251: CUST020 | D251: Margaret Wright | E251: P010 | F251: Keyboard | G251: Electronics | H251: 5 | I251: 89.99 | J251: PayPal | K251: South | L251: Basic | M251: 44704 | N251: 449.95

Sheet analysis
A1: Top customers by each categoruies | E1: Top revenue by each category | H1: most sold product by each category | L1: most sold product by each category
B2: max purchase value | F2: revenue total | G2: =IF(C2=4499.95,A2," ") | I2: most sold qty | J2: most sold product name | M2: most sold qty | N2: most sold product name
A3: Electronics | B3: =MAX(D7:D256) -> 4499.95 | C3: Robert Thomas | D3: =_xlfn.MAXIFS(C6:C256,B6:B256,A3) -> 4499.95 | E3: Appliances | F3: =SUMIF(B6:B256,E3,C6:C256) -> 8338.74 | G3: =IF(C3=4499.95,A3," ") | H3: Appliances | I3: =_xlfn.MAXIFS(Table1[Quantity],Table1[Category],analysis!H3) -> 5 | J3: =INDEX(Table1[],MATCH(I3,Table1[Quantity],0),MATCH(Table1[[#Headers],[Product_Name]],Table1[#Headers],0)) -> Headphones | K3: 5 | L3: Appliances | M3: =_xlfn.MAXIFS(Table1[Quantity],Table1[Category],analysis!L3) -> 5 | N3: Blender | R3: Row Labels | S3: Sum of Quantity
A4: Appliances | B4: =MAX(E7:E256) -> 399.95 | C4: =H106 -> Carol Evans | D4: =_xlfn.MAXIFS(C7:C257,B7:B257,A4) -> 399.95 | E4: Electronics | F4: =SUMIF(B7:B257,E4,C7:C257) -> 171756.05 | G4: =IF(C4=4499.95,A4," ") | H4: Electronics | I4: =_xlfn.MAXIFS(Table1[Quantity],Table1[Category],analysis!H4) -> 5 | J4: =INDEX(Table1[],MATCH(I4,Table1[Quantity],0),MATCH(Table1[[#Headers],[Product_Name]],Table1[#Headers],0)) -> Headphones | K4: =VLOOKUP(H4,'Final Project Dataset'!G2:H252,2,0) -> 3 | L4: Electronics | M4: =_xlfn.MAXIFS(Table1[Quantity],Table1[Category],analysis!L4) -> 5 | N4: Headphones | R4: Appliances | S4: 126
A5: Furniture | B5: =MAX(F7:F256) -> 1499.95 | C5: Paul Baker | D5: =_xlfn.MAXIFS(C8:C258,B8:B258,A5) -> 1499.95 | E5: Furniture | F5: =SUMIF(B8:B258,E5,C8:C258) -> 49097.68 | G5: =IF(C5=4499.95,A5," ") | H5: Furniture | I5: =_xlfn.MAXIFS(Table1[Quantity],Table1[Category],analysis!H5) -> 5 | J5: =INDEX(Table1[],MATCH(I5,Table1[Quantity],0),MATCH(Table1[[#Headers],[Product_Name]],Table1[#Headers],0)) -> Headphones | K5: =VLOOKUP(H5,'Final Project Dataset'!G3:H253,2,0) -> 5 | L5: Furniture | M5: =_xlfn.MAXIFS(Table1[Quantity],Table1[Category],analysis!L5) -> 5 | N5: Bookshelf | R5: Blender | S5: 87
A6: Customer_Name | B6: Category | C6: Total_Amount | D6: if elctronics | E6: if applince | F6: if furnichers | G6: =IF(C6=4499.95,A6," ") | H6: =IF(C6=$B$4,A6,"") | I6: =IF(C6=$B$5,A6,"") | R6: Coffee Maker | S6: 39
A7: Paul Baker | B7: Appliances | C7: 59.99 | D7: =IF(B7=$A$3,C7,$G$7) | E7: =IF(B7=$A$4,C7,$G$7) -> 59.99 | F7: =IF(B7=$A$5,C7,$H$7) | G7: =IF(C7=4499.95,A7," ") | H7: =IF(C7=$B$4,A7,"") | I7: =IF(C7=$B$5,A7,"") | R7: Electronics | S7: 395
A8: Joseph Jackson | B8: Appliances | C8: 59.99 | D8: =IF(B8=$A$3,C8,$G$7) | E8: =IF(B8=$A$4,C8,$G$7) -> 59.99 | F8: =IF(B8=$A$5,C8,$H$7) | G8: =IF(C8=4499.95,A8," ") | H8: =IF(C8=$B$4,A8,"") | I8: =IF(C8=$B$5,A8,"") | K8: Quantity | L8: Category | M8: Product_Name | N8: =L3 -> Appliances | O8: =L4 -> Electronics | P8: =L5 -> Furniture | R8: Headphones | S8: 47
A9: Kevin Scott | B9: Appliances | C9: 59.99 | D9: =IF(B9=$A$3,C9,$G$7) | E9: =IF(B9=$A$4,C9,$G$7) -> 59.99 | F9: =IF(B9=$A$5,C9,$H$7) | G9: =IF(C9=4499.95,A9," ") | H9: =IF(C9=$B$4,A9,"") | I9: =IF(C9=$B$5,A9,"") | K9: =Table1[[#This Row],[Quantity]] -> 1 | L9: =Table1[[#This Row],[Category]] -> Electronics | M9: =Table1[[#This Row],[Product_Name]] -> Keyboard | N9: =IF(AND(K9=$M$3,L9=$L$3),M9,"") | O9: =IF(AND(K9=M4,L9=$O$8),M9,"no") -> no | P9: =IF(AND(K9=$M$5,L9=$P$8),M9,"no") -> no | R9: Keyboard | S9: 89
A10: Kathleen Bennett | B10: Appliances | C10: 79.99 | D10: =IF(B10=$A$3,C10,$G$7) | E10: =IF(B10=$A$4,C10,$G$7) -> 79.99 | F10: =IF(B10=$A$5,C10,$H$7) | G10: =IF(C10=4499.95,A10," ") | H10: =IF(C10=$B$4,A10,"") | I10: =IF(C10=$B$5,A10,"") | K10: =Table1[[#This Row],[Quantity]] -> 1 | L10: =Table1[[#This Row],[Category]] -> Electronics | M10: =Table1[[#This Row],[Product_Name]] -> Headphones | N10: =IF(AND(K10=$M$3,L10=$L$3),M10,"no") -> no | O10: =IF(AND(K10=M5,L10=$O$8),M10,"no") -> no | P10: =IF(AND(K10=$M$5,L10=$P$8),M10,"no") -> no | R10: Laptop | S10: 75
A11: Michael Brown | B11: Appliances | C11: 79.99 | D11: =IF(B11=$A$3,C11,$G$7) | E11: =IF(B11=$A$4,C11,$G$7) -> 79.99 | F11: =IF(B11=$A$5,C11,$H$7) | G11: =IF(C11=4499.95,A11," ") | H11: =IF(C11=$B$4,A11,"") | I11: =IF(C11=$B$5,A11,"") | K11: =Table1[[#This Row],[Quantity]] -> 1 | L11: =Table1[[#This Row],[Category]] -> Electronics | M11: =Table1[[#This Row],[Product_Name]] -> Laptop | N11: =IF(AND(K11=$M$3,L11=$L$3),M11,"no") -> no | O11: =IF(AND(K11=M6,L11=$O$8),M11,"no") -> no | P11: =IF(AND(K11=$M$5,L11=$P$8),M11,"no") -> no | R11: Monitor | S11: 88
A12: Dorothy Nelson | B12: Appliances | C12: 79.99 | D12: =IF(B12=$A$3,C12,$G$7) | E12: =IF(B12=$A$4,C12,$G$7) -> 79.99 | F12: =IF(B12=$A$5,C12,$H$7) | G12: =IF(C12=4499.95,A12," ") | H12: =IF(C12=$B$4,A12,"") | I12: =IF(C12=$B$5,A12,"") | K12: =Table1[[#This Row],[Quantity]] -> 1 | L12: =Table1[[#This Row],[Category]] -> Appliances | M12: =Table1[[#This Row],[Product_Name]] -> Coffee Maker | N12: =IF(AND(K12=$M$3,L12=$L$3),M12,"no") -> no | O12: =IF(AND(K12=M7,L12=$O$8),M12,"no") -> no | P12: =IF(AND(K12=$M$5,L12=$P$8),M12,"no") -> no | R12: Smartphone | S12: 96
A13: Dorothy Nelson | B13: Appliances | C13: 79.99 | D13: =IF(B13=$A$3,C13,$G$7) | E13: =IF(B13=$A$4,C13,$G$7) -> 79.99 | F13: =IF(B13=$A$5,C13,$H$7) | G13: =IF(C13=4499.95,A13," ") | H13: =IF(C13=$B$4,A13,"") | I13: =IF(C13=$B$5,A13,"") | K13: =Table1[[#This Row],[Quantity]] -> 1 | L13: =Table1[[#This Row],[Category]] -> Furniture | M13: =Table1[[#This Row],[Product_Name]] -> Bookshelf | N13: =IF(AND(K13=$M$3,L13=$L$3),M13,"no") -> no | O13: =IF(AND(K13=M8,L13=$O$8),M13,"no") -> no | P13: =IF(AND(K13=$M$5,L13=$P$8),M13,"no") -> no | R13: Furniture | S13: 232
A14: Charles Allen | B14: Electronics | C14: 89.99 | D14: =IF(B14=$A$3,C14,$G$7) -> 89.99 | E14: =IF(B14=$A$4,C14,$G$7) | F14: =IF(B14=$A$5,C14,$H$7) | G14: =IF(C14=4499.95,A14," ") | H14: =IF(C14=$B$4,A14,"") | I14: =IF(C14=$B$5,A14,"") | K14: =Table1[[#This Row],[Quantity]] -> 1 | L14: =Table1[[#This Row],[Category]] -> Furniture | M14: =Table1[[#This Row],[Product_Name]] -> Bookshelf | N14: =IF(AND(K14=$M$3,L14=$L$3),M14,"no") -> no | O14: =IF(AND(K14=M9,L14=$O$8),M14,"no") -> no | P14: =IF(AND(K14=$M$5,L14=$P$8),M14,"no") -> no | R14: Bookshelf | S14: 102
A15: Robert Thomas | B15: Electronics | C15: 89.99 | D15: =IF(B15=$A$3,C15,$G$7) -> 89.99 | E15: =IF(B15=$A$4,C15,$G$7) | F15: =IF(B15=$A$5,C15,$H$7) | G15: =IF(C15=4499.95,A15," ") | I15: =IF(C15=$B$5,A15,"") | K15: =Table1[[#This Row],[Quantity]] -> 1 | L15: =Table1[[#This Row],[Category]] -> Electronics | M15: =Table1[[#This Row],[Product_Name]] -> Keyboard | N15: =IF(AND(K15=$M$3,L15=$L$3),M15,"no") -> no | O15: =IF(AND(K15=M10,L15=$O$8),M15,"no") -> no | P15: =IF(AND(K15=$M$5,L15=$P$8),M15,"no") -> no | R15: Desk | S15: 78
A16: Karen Hill | B16: Electronics | C16: 89.99 | D16: =IF(B16=$A$3,C16,$G$7) -> 89.99 | E16: =IF(B16=$A$4,C16,$G$7) | F16: =IF(B16=$A$5,C16,$H$7) | K16: =Table1[[#This Row],[Quantity]] -> 1 | L16: =Table1[[#This Row],[Category]] -> Appliances | M16: =Table1[[#This Row],[Product_Name]] -> Coffee Maker | N16: =IF(AND(K16=$M$3,L16=$L$3),M16,"no") -> no | O16: =IF(AND(K16=M11,L16=$O$8),M16,"no") -> no | P16: =IF(AND(K16=$M$5,L16=$P$8),M16,"no") -> no | R16: Office Chair | S16: 52
A17: Susan Green | B17: Electronics | C17: 89.99 | D17: =IF(B17=$A$3,C17,$G$7) -> 89.99 | E17: =IF(B17=$A$4,C17,$G$7) | F17: =IF(B17=$A$5,C17,$H$7) | K17: =Table1[[#This Row],[Quantity]] -> 1 | L17: =Table1[[#This Row],[Category]] -> Electronics | M17: =Table1[[#This Row],[Product_Name]] -> Smartphone | N17: =IF(AND(K17=$M$3,L17=$L$3),M17,"no") -> no | O17: =IF(AND(K17=M12,L17=$O$8),M17,"no") -> no | P17: =IF(AND(K17=$M$5,L17=$P$8),M17,"no") -> no | R17: Grand Total | S17: 753
A18: Kathleen Bennett | B18: Electronics | C18: 89.99 | D18: =IF(B18=$A$3,C18,$G$7) -> 89.99 | E18: =IF(B18=$A$4,C18,$G$7) | F18: =IF(B18=$A$5,C18,$H$7) | K18: =Table1[[#This Row],[Quantity]] -> 1 | L18: =Table1[[#This Row],[Category]] -> Electronics | M18: =Table1[[#This Row],[Product_Name]] -> Monitor | N18: =IF(AND(K18=$M$3,L18=$L$3),M18,"no") -> no | O18: =IF(AND(K18=M13,L18=$O$8),M18,"no") -> no | P18: =IF(AND(K18=$M$5,L18=$P$8),M18,"no") -> no
A19: Peter Richardson | B19: Electronics | C19: 89.99 | D19: =IF(B19=$A$3,C19,$G$7) -> 89.99 | E19: =IF(B19=$A$4,C19,$G$7) | F19: =IF(B19=$A$5,C19,$H$7) | K19: =Table1[[#This Row],[Quantity]] -> 1 | L19: =Table1[[#This Row],[Category]] -> Furniture | M19: =Table1[[#This Row],[Product_Name]] -> Bookshelf | N19: =IF(AND(K19=$M$3,L19=$L$3),M19,"no") -> no | O19: =IF(AND(K19=M14,L19=$O$8),M19,"no") -> no | P19: =IF(AND(K19=$M$5,L19=$P$8),M19,"no") -> no
A20: Dennis Gray | B20: Electronics | C20: 89.99 | D20: =IF(B20=$A$3,C20,$G$7) -> 89.99 | E20: =IF(B20=$A$4,C20,$G$7) | F20: =IF(B20=$A$5,C20,$H$7) | G20: =IF(C20=4499.95,A20," ") | H20: =IF(C20=$B$4,A20,"") | I20: =IF(C20=$B$5,A20,"") | K20: =Table1[[#This Row],[Quantity]] -> 1 | L20: =Table1[[#This Row],[Category]] -> Electronics | M20: =Table1[[#This Row],[Product_Name]] -> Monitor | N20: =IF(AND(K20=$M$3,L20=$L$3),M20,"no") -> no | O20: =IF(AND(K20=M15,L20=$O$8),M20,"no") -> no | P20: =IF(AND(K20=$M$5,L20=$P$8),M20,"no") -> no
A21: Michelle Rogers | B21: Electronics | C21: 89.99 | D21: =IF(B21=$A$3,C21,$G$7) -> 89.99 | E21: =IF(B21=$A$4,C21,$G$7) | F21: =IF(B21=$A$5,C21,$H$7) | G21: =IF(C21=4499.95,A21," ") | H21: =IF(C21=$B$4,A21,"") | I21: =IF(C21=$B$5,A21,"") | K21: =Table1[[#This Row],[Quantity]] -> 1 | L21: =Table1[[#This Row],[Category]] -> Furniture | M21: =Table1[[#This Row],[Product_Name]] -> Desk | N21: =IF(AND(K21=$M$3,L21=$L$3),M21,"no") -> no | O21: =IF(AND(K21=M16,L21=$O$8),M21,"no") -> no | P21: =IF(AND(K21=$M$5,L21=$P$8),M21,"no") -> no
A22: George Adams | B22: Appliances | C22: 119.98 | D22: =IF(B22=$A$3,C22,$G$7) | E22: =IF(B22=$A$4,C22,$G$7) -> 119.98 | F22: =IF(B22=$A$5,C22,$H$7) | G22: =IF(C22=4499.95,A22," ") | H22: =IF(C22=$B$4,A22,"") | I22: =IF(C22=$B$5,A22,"") | K22: =Table1[[#This Row],[Quantity]] -> 1 | L22: =Table1[[#This Row],[Category]] -> Electronics | M22: =Table1[[#This Row],[Product_Name]] -> Headphones | N22: =IF(AND(K22=$M$3,L22=$L$3),M22,"no") -> no | O22: =IF(AND(K22=M17,L22=$O$8),M22,"no") -> no | P22: =IF(AND(K22=$M$5,L22=$P$8),M22,"no") -> no
A23: Mark Carter | B23: Appliances | C23: 119.98 | D23: =IF(B23=$A$3,C23,$G$7) | E23: =IF(B23=$A$4,C23,$G$7) -> 119.98 | F23: =IF(B23=$A$5,C23,$H$7) | G23: =IF(C23=4499.95,A23," ") | H23: =IF(C23=$B$4,A23,"") | I23: =IF(C23=$B$5,A23,"") | K23: =Table1[[#This Row],[Quantity]] -> 1 | L23: =Table1[[#This Row],[Category]] -> Appliances | M23: =Table1[[#This Row],[Product_Name]] -> Blender | N23: =IF(AND(K23=$M$3,L23=$L$3),M23,"no") -> no | O23: =IF(AND(K23=M18,L23=$O$8),M23,"no") -> no | P23: =IF(AND(K23=$M$5,L23=$P$8),M23,"no") -> no
A24: Maria Garcia | B24: Appliances | C24: 119.98 | D24: =IF(B24=$A$3,C24,$G$7) | E24: =IF(B24=$A$4,C24,$G$7) -> 119.98 | F24: =IF(B24=$A$5,C24,$H$7) | G24: =IF(C24=4499.95,A24," ") | H24: =IF(C24=$B$4,A24,"") | I24: =IF(C24=$B$5,A24,"") | K24: =Table1[[#This Row],[Quantity]] -> 1 | L24: =Table1[[#This Row],[Category]] -> Furniture | M24: =Table1[[#This Row],[Product_Name]] -> Desk | N24: =IF(AND(K24=$M$3,L24=$L$3),M24,"no") -> no | O24: =IF(AND(K24=M19,L24=$O$8),M24,"no") -> no | P24: =IF(AND(K24=$M$5,L24=$P$8),M24,"no") -> no
A25: Mark Carter | B25: Appliances | C25: 119.98 | D25: =IF(B25=$A$3,C25,$G$7) | E25: =IF(B25=$A$4,C25,$G$7) -> 119.98 | F25: =IF(B25=$A$5,C25,$H$7) | G25: =IF(C25=4499.95,A25," ") | H25: =IF(C25=$B$4,A25,"") | I25: =IF(C25=$B$5,A25,"") | K25: =Table1[[#This Row],[Quantity]] -> 1 | L25: =Table1[[#This Row],[Category]] -> Electronics | M25: =Table1[[#This Row],[Product_Name]] -> Laptop | N25: =IF(AND(K25=$M$3,L25=$L$3),M25,"no") -> no | O25: =IF(AND(K25=M20,L25=$O$8),M25,"no") -> no | P25: =IF(AND(K25=$M$5,L25=$P$8),M25,"no") -> no
A26: Virginia Sanders | B26: Appliances | C26: 119.98 | D26: =IF(B26=$A$3,C26,$G$7) | E26: =IF(B26=$A$4,C26,$G$7) -> 119.98 | F26: =IF(B26=$A$5,C26,$H$7) | G26: =IF(C26=4499.95,A26," ") | H26: =IF(C26=$B$4,A26,"") | I26: =IF(C26=$B$5,A26,"") | K26: =Table1[[#This Row],[Quantity]] -> 1 | L26: =Table1[[#This Row],[Category]] -> Electronics | M26: =Table1[[#This Row],[Product_Name]] -> Monitor | N26: =IF(AND(K26=$M$3,L26=$L$3),M26,"no") -> no | O26: =IF(AND(K26=M21,L26=$O$8),M26,"no") -> no | P26: =IF(AND(K26=$M$5,L26=$P$8),M26,"no") -> no
A27: Barbara Young | B27: Appliances | C27: 119.98 | D27: =IF(B27=$A$3,C27,$G$7) | E27: =IF(B27=$A$4,C27,$G$7) -> 119.98 | F27: =IF(B27=$A$5,C27,$H$7) | G27: =IF(C27=4499.95,A27," ") | H27: =IF(C27=$B$4,A27,"") | I27: =IF(C27=$B$5,A27,"") | K27: =Table1[[#This Row],[Quantity]] -> 1 | L27: =Table1[[#This Row],[Category]] -> Furniture | M27: =Table1[[#This Row],[Product_Name]] -> Office Chair | N27: =IF(AND(K27=$M$3,L27=$L$3),M27,"no") -> no | O27: =IF(AND(K27=M22,L27=$O$8),M27,"no") -> no | P27: =IF(AND(K27=$M$5,L27=$P$8),M27,"no") -> no
A28: Patricia Moore | B28: Appliances | C28: 119.98 | D28: =IF(B28=$A$3,C28,$G$7) | E28: =IF(B28=$A$4,C28,$G$7) -> 119.98 | F28: =IF(B28=$A$5,C28,$H$7) | G28: =IF(C28=4499.95,A28," ") | H28: =IF(C28=$B$4,A28,"") | I28: =IF(C28=$B$5,A28,"") | K28: =Table1[[#This Row],[Quantity]] -> 1 | L28: =Table1[[#This Row],[Category]] -> Furniture | M28: =Table1[[#This Row],[Product_Name]] -> Bookshelf | N28: =IF(AND(K28=$M$3,L28=$L$3),M28,"no") -> no | O28: =IF(AND(K28=M23,L28=$O$8),M28,"no") -> no | P28: =IF(AND(K28=$M$5,L28=$P$8),M28,"no") -> no
A29: Cynthia Price | B29: Furniture | C29: 149.99 | D29: =IF(B29=$A$3,C29,$G$7) | E29: =IF(B29=$A$4,C29,$G$7) | F29: =IF(B29=$A$5,C29,$H$7) -> 149.99 | G29: =IF(C29=4499.95,A29," ") | H29: =IF(C29=$B$4,A29,"") | I29: =IF(C29=$B$5,A29,"") | K29: =Table1[[#This Row],[Quantity]] -> 1 | L29: =Table1[[#This Row],[Category]] -> Appliances | M29: =Table1[[#This Row],[Product_Name]] -> Coffee Maker | N29: =IF(AND(K29=$M$3,L29=$L$3),M29,"no") -> no | O29: =IF(AND(K29=M24,L29=$O$8),M29,"no") -> no | P29: =IF(AND(K29=$M$5,L29=$P$8),M29,"no") -> no
A30: Mark Carter | B30: Electronics | C30: 149.99 | D30: =IF(B30=$A$3,C30,$G$7) -> 149.99 | E30: =IF(B30=$A$4,C30,$G$7) | F30: =IF(B30=$A$5,C30,$H$7) | G30: =IF(C30=4499.95,A30," ") | H30: =IF(C30=$B$4,A30,"") | I30: =IF(C30=$B$5,A30,"") | K30: =Table1[[#This Row],[Quantity]] -> 1 | L30: =Table1[[#This Row],[Category]] -> Electronics | M30: =Table1[[#This Row],[Product_Name]] -> Keyboard | N30: =IF(AND(K30=$M$3,L30=$L$3),M30,"no") -> no | O30: =IF(AND(K30=M25,L30=$O$8),M30,"no") -> no | P30: =IF(AND(K30=$M$5,L30=$P$8),M30,"no") -> no
A31: Nancy Collins | B31: Electronics | C31: 149.99 | D31: =IF(B31=$A$3,C31,$G$7) -> 149.99 | E31: =IF(B31=$A$4,C31,$G$7) | F31: =IF(B31=$A$5,C31,$H$7) | G31: =IF(C31=4499.95,A31," ") | H31: =IF(C31=$B$4,A31,"") | I31: =IF(C31=$B$5,A31,"") | K31: =Table1[[#This Row],[Quantity]] -> 1 | L31: =Table1[[#This Row],[Category]] -> Furniture | M31: =Table1[[#This Row],[Product_Name]] -> Desk | N31: =IF(AND(K31=$M$3,L31=$L$3),M31,"no") -> no | O31: =IF(AND(K31=M26,L31=$O$8),M31,"no") -> no | P31: =IF(AND(K31=$M$5,L31=$P$8),M31,"no") -> no
... A251: Edward Mitchell | B251: Electronics | C251: 4499.95 | D251: =IF(B251=$A$3,C251,$G$7) -> 4499.95 | E251: =IF(B251=$A$4,C251,$G$7) | F251: =IF(B251=$A$5,C251,$H$7) | G251: =IF(C251=4499.95,A251," ") -> Edward Mitchell | H251: =IF(C251=$B$4,A251,"") | I251: =IF(C251=$B$5,A251,"") | K251: =Table1[[#This Row],[Quantity]] -> 5 | L251: =Table1[[#This Row],[Category]] -> Electronics | M251: =Table1[[#This Row],[Product_Name]] -> Keyboard | N251: =IF(AND(K251=$M$3,L251=$L$3),M251,"no") -> no | O251: =IF(AND(K251=M246,L251=$O$8),M251,"no") -> no | P251: =IF(AND(K251=$M$5,L251=$P$8),M251,"no") -> no
A252: Virginia Sanders | B252: Electronics | C252: 4499.95 | D252: =IF(B252=$A$3,C252,$G$7) -> 4499.95 | E252: =IF(B252=$A$4,C252,$G$7) | F252: =IF(B252=$A$5,C252,$H$7) | G252: =IF(C252=4499.95,A252," ") -> Virginia Sanders | H252: =IF(C252=$B$4,A252,"") | I252: =IF(C252=$B$5,A252,"")
A253: Robert Thomas | B253: Electronics | C253: 4499.95 | D253: =IF(B253=$A$3,C253,$G$7) -> 4499.95 | E253: =IF(B253=$A$4,C253,$G$7) | F253: =IF(B253=$A$5,C253,$H$7) | G253: =IF(C253=4499.95,A253," ") -> Robert Thomas | H253: =IF(C253=$B$4,A253,"") | I253: =IF(C253=$B$5,A253,"") | L253: =Table1[[#This Row],[Product_Name]] -> #VALUE!
A254: Douglas Watson | B254: Electronics | C254: 4499.95 | D254: =IF(B254=$A$3,C254,$G$7) -> 4499.95 | E254: =IF(B254=$A$4,C254,$G$7) | F254: =IF(B254=$A$5,C254,$H$7) | G254: =IF(C254=4499.95,A254," ") -> Douglas Watson | H254: =IF(C254=$B$4,A254,"") | I254: =IF(C254=$B$5,A254,"") | L254: =Table1[[#This Row],[Product_Name]] -> #VALUE!
A255: Lawrence Reed | B255: Electronics | C255: 4499.95 | D255: =IF(B255=$A$3,C255,$G$7) -> 4499.95 | E255: =IF(B255=$A$4,C255,$G$7) | F255: =IF(B255=$A$5,C255,$H$7) | G255: =IF(C255=4499.95,A255," ") -> Lawrence Reed | H255: =IF(C255=$B$4,A255,"") | I255: =IF(C255=$B$5,A255,"") | L255: =Table1[[#This Row],[Product_Name]] -> #VALUE!
A256: Steven Turner | B256: Electronics | C256: 4499.95 | D256: =IF(B256=$A$3,C256,$G$7) -> 4499.95 | E256: =IF(B256=$A$4,C256,$G$7) | F256: =IF(B256=$A$5,C256,$H$7) | G256: =IF(C256=4499.95,A256," ") -> Steven Turner | H256: =IF(C256=$B$4,A256,"") | I256: =IF(C256=$B$5,A256,"") | L256: =Table1[[#This Row],[Product_Name]] -> #VALUE!

Sheet Final Project Dataset
A1: Transaction_ID | B1: Date | C1: Customer_ID | D1: Customer_Name | E1: Product_ID | F1: Product_Name | G1: Category | H1: Quantity | I1: Unit_Price | J1: Payment_Method | K1: Region | L1: Customer_Segment | M1: Customer_Since | N1: Total_Amount
A2: TRX0155 | B2: 45393 | C2: CUST023 | D2: Paul Baker | E2: P009 | F2: Monitor | G2: Electronics | H2: 3 | I2: 249.99 | J2: Cash | K2: Central | L2: Basic | M2: 44425 | N2: 749.97
A3: TRX0023 | B3: 45396 | C3: CUST013 | D3: Joseph Jackson | E3: P009 | F3: Monitor | G3: Electronics | H3: 3 | I3: 249.99 | J3: Credit Card | K3: Central | L3: Premium | M3: 44575 | N3: 749.97
A4: TRX0139 | B4: 45399 | C4: CUST021 | D4: Kevin Scott | E4: P005 | F4: Blender | G4: Appliances | H4: 3 | I4: 59.99 | J4: PayPal | K4: South | L4: Standard | M4: 45262 | N4: 179.97
A5: TRX0043 | B5: 45400 | C5: CUST046 | D5: Kathleen Bennett | E5: P005 | F5: Blender | G5: Appliances | H5: 3 | I5: 59.99 | J5: Cash | K5: North | L5: Premium | M5: 45114 | N5: 179.97
A6: TRX0212 | B6: 45400 | C6: CUST003 | D6: Michael Brown | E6: P008 | F6: Bookshelf | G6: Furniture | H6: 5 | I6: 149.99 | J6: Credit Card | K6: North | L6: Premium | M6: 45295 | N6: 749.95
A7: TRX0092 | B7: 45403 | C7: CUST024 | D7: Dorothy Nelson | E7: P005 | F7: Blender | G7: Appliances | H7: 2 | I7: 59.99 | J7: Cash | K7: West | L7: Standard | M7: 44746 | N7: 119.98
A8: TRX0193 | B8: 45403 | C8: CUST024 | D8: Dorothy Nelson | E8: P003 | F8: Headphones | G8: Electronics | H8: 5 | I8: 149.99 | J8: Credit Card | K8: Central | L8: Standard | M8: 44418 | N8: 749.95
A9: TRX0240 | B9: 45403 | C9: CUST017 | D9: Charles Allen | E9: P005 | F9: Blender | G9: Appliances | H9: 3 | I9: 59.99 | J9: Debit Card | K9: South | L9: Basic | M9: 45007 | N9: 179.97
A10: TRX0135 | B10: 45405 | C10: CUST009 | D10: Robert Thomas | E10: P001 | F10: Laptop | G10: Electronics | H10: 3 | I10: 899.99 | J10: PayPal | K10: East | L10: Standard | M10: 45299 | N10: 2699.97
A11: TRX0185 | B11: 45408 | C11: CUST026 | D11: Karen Hill | E11: P005 | F11: Blender | G11: Appliances | H11: 3 | I11: 59.99 | J11: Cash | K11: West | L11: Premium | M11: 45207 | N11: 179.97
A12: TRX0138 | B12: 45408 | C12: CUST022 | D12: Susan Green | E12: P008 | F12: Bookshelf | G12: Furniture | H12: 1 | I12: 149.99 | J12: Credit Card | K12: West | L12: Standard | M12: 45103 | N12: 149.99
A13: TRX0209 | B13: 45408 | C13: CUST046 | D13: Kathleen Bennett | E13: P008 | F13: Bookshelf | G13: Furniture | H13: 5 | I13: 149.99 | J13: Debit Card | K13: North | L13: Basic | M13: 44830 | N13: 749.95
... A251: TRX0064 | B251: 45758 | C251: CUST031 | D251: Steven Turner | E251: P010 | F251: Keyboard | G251: Electronics | H251: 3 | I251: 89.99 | J251: Debit Card | K251: North | L251: Premium | M251: 44878 | N251: 269.97

Sheet Q1 DATE function
A1: Customer_Since | B1: Date | C1: Date Dif | D1: EoMonth | E1: Today | F1: now | H1: filter function
A2: 44425 | B2: 45393 | C2: =DATEDIF(A2,B2,"m") -> 31 | D2: =EOMONTH(B2,MONTH(B2)) -> 45535 | E2: =TODAY() -> 45971 | F2: =NOW() -> 45971.846
A3: 44575 | B3: 45396 | C3: =DATEDIF(A3,B3,"m") -> 27 | D3: =EOMONTH(B3,MONTH(B3)) -> 45535
A4: 45262 | B4: 45399 | C4: =DATEDIF(A4,B4,"m") -> 4 | D4: =EOMONTH(B4,MONTH(B4)) -> 45535
A5: 45114 | B5: 45400 | C5: =DATEDIF(A5,B5,"m") -> 9 | D5: =EOMONTH(B5,MONTH(B5)) -> 45535
A6: 45295 | B6: 45400 | C6: =DATEDIF(A6,B6,"m") -> 3 | D6: =EOMONTH(B6,MONTH(B6)) -> 45535
A7: 44746 | B7: 45403 | C7: =DATEDIF(A7,B7,"m") -> 21 | D7: =EOMONTH(B7,MONTH(B7)) -> 45535
A8: 44418 | B8: 45403 | C8: =DATEDIF(A8,B8,"m") -> 32 | D8: =EOMONTH(B8,MONTH(B8)) -> 45535
A9: 45007 | B9: 45403 | C9: =DATEDIF(A9,B9,"m") -> 12 | D9: =EOMONTH(B9,MONTH(B9)) -> 45535
A10: 45299 | B10: 45405 | C10: =DATEDIF(A10,B10,"m") -> 3 | D10: =EOMONTH(B10,MONTH(B10)) -> 45535
A11: 45207 | B11: 45408 | C11: =DATEDIF(A11,B11,"m") -> 6 | D11: =EOMONTH(B11,MONTH(B11)) -> 45535
A12: 45103 | B12: 45408 | C12: =DATEDIF(A12,B12,"m") -> 10 | D12: =EOMONTH(B12,MONTH(B12)) -> 45535
A13: 44830 | B13: 45408 | C13: =DATEDIF(A13,B13,"m") -> 19 | D13: =EOMONTH(B13,MONTH(B13)) -> 45535
A14: 44806 | B14: 45408 | C14: =DATEDIF(A14,B14,"m") -> 19 | D14: =EOMONTH(B14,MONTH(B14)) -> 45535
... A251: 44878 | B251: 45758 | C251: =DATEDIF(A251,B251,"m") -> 28 | D251: =EOMONTH(B251,MONTH(B251)) -> 45900

Sheet Q2 filter fuction 
A1: filter function
A2: {=_xlfn._xlws.FILTER(Table1[],Table1[Category]='Final Project Dataset'!$G$2)} -> TRX0230 | B2: 45409 | C2: CUST027 | D2: George Adams | E2: P001 | F2: Laptop | G2: Electronics | H2: 1 | I2: 899.99 | J2: Debit Card | K2: North | L2: Standard | M2: 44920 | N2: 899.99
A3: TRX0041 | B3: 45432 | C3: CUST021 | D3: Kevin Scott | E3: P001 | F3: Laptop | G3: Electronics | H3: 1 | I3: 899.99 | J3: Credit Card | K3: West | L3: Premium | M3: 44578 | N3: 899.99
A4: TRX0117 | B4: 45444 | C4: CUST017 | D4: Charles Allen | E4: P010 | F4: Keyboard | G4: Electronics | H4: 1 | I4: 89.99 | J4: Cash | K4: North | L4: Basic | M4: 45141 | N4: 89.99
A5: TRX0121 | B5: 45449 | C5: CUST028 | D5: Betty Campbell | E5: P010 | F5: Keyboard | G5: Electronics | H5: 1 | I5: 89.99 | J5: Credit Card | K5: South | L5: Standard | M5: 44582 | N5: 89.99
A6: TRX0192 | B6: 45475 | C6: CUST017 | D6: Charles Allen | E6: P010 | F6: Keyboard | G6: Electronics | H6: 1 | I6: 89.99 | J6: PayPal | K6: West | L6: Standard | M6: 44802 | N6: 89.99
A7: TRX0052 | B7: 45476 | C7: CUST022 | D7: Susan Green | E7: P010 | F7: Keyboard | G7: Electronics | H7: 1 | I7: 89.99 | J7: Cash | K7: South | L7: Standard | M7: 44611 | N7: 89.99
A8: TRX0018 | B8: 45484 | C8: CUST013 | D8: Joseph Jackson | E8: P003 | F8: Headphones | G8: Electronics | H8: 1 | I8: 149.99 | J8: Cash | K8: Central | L8: Standard | M8: 44909 | N8: 149.99
A9: TRX0162 | B9: 45496 | C9: CUST040 | D9: Sharon Butler | E9: P001 | F9: Laptop | G9: Electronics | H9: 1 | I9: 899.99 | J9: Cash | K9: Central | L9: Standard | M9: 45179 | N9: 899.99
A10: TRX0101 | B10: 45513 | C10: CUST010 | D10: Maria Garcia | E10: P010 | F10: Keyboard | G10: Electronics | H10: 1 | I10: 89.99 | J10: Credit Card | K10: North | L10: Standard | M10: 45393 | N10: 89.99
A11: TRX0058 | B11: 45532 | C11: CUST047 | D11: Gerald Murphy | E11: P002 | F11: Smartphone | G11: Electronics | H11: 1 | I11: 699.99 | J11: Cash | K11: Central | L11: Premium | M11: 44497 | N11: 699.99
A12: TRX0099 | B12: 45537 | C12: CUST034 | D12: Carol Evans | E12: P009 | F12: Monitor | G12: Electronics | H12: 1 | I12: 249.99 | J12: Credit Card | K12: West | L12: Premium | M12: 44685 | N12: 249.99
A13: TRX0074 | B13: 45537 | C13: CUST023 | D13: Paul Baker | E13: P009 | F13: Monitor | G13: Electronics | H13: 1 | I13: 249.99 | J13: Debit Card | K13: North | L13: Premium | M13: 45332 | N13: 249.99
A14: TRX0111 | B14: 45554 | C14: CUST011 | D14: William White | E14: P003 | F14: Headphones | G14: Electronics | H14: 1 | I14: 149.99 | J14: PayPal | K14: East | L14: Standard | M14: 44482 | N14: 149.99
... A132: TRX0213 | B132: 45745 | C132: CUST020 | D132: Margaret Wright | E132: P010 | F132: Keyboard | G132: Electronics | H132: 5 | I132: 89.99 | J132: PayPal | K132: South | L132: Basic | M132: 44704 | N132: 449.95

Sheet Q3 Conditiona l fornamting
A1: Transaction_ID | B1: Date | C1: Customer_ID | D1: Customer_Name | E1: Product_ID | F1: Product_Name | G1: Category | H1: Quantity | I1: Unit_Price | J1: Payment_Method | K1: Region | L1: Customer_Segment | M1: Customer_Since | N1: Total_Amount
A2: TRX0155 | B2: 45393 | C2: CUST023 | D2: Paul Baker | E2: P009 | F2: Monitor | G2: Electronics | H2: 3 | I2: 249.99 | J2: Cash | K2: Central | L2: Basic | M2: 44425 | N2: 749.97
A3: TRX0023 | B3: 45396 | C3: CUST013 | D3: Joseph Jackson | E3: P009 | F3: Monitor | G3: Electronics | H3: 3 | I3: 249.99 | J3: Credit Card | K3: Central | L3: Premium | M3: 44575 | N3: 749.97
A4: TRX0139 | B4: 45399 | C4: CUST021 | D4: Kevin Scott | E4: P005 | F4: Blender | G4: Appliances | H4: 3 | I4: 59.99 | J4: PayPal | K4: South | L4: Standard | M4: 45262 | N4: 179.97
A5: TRX0043 | B5: 45400 | C5: CUST046 | D5: Kathleen Bennett | E5: P005 | F5: Blender | G5: Appliances | H5: 3 | I5: 59.99 | J5: Cash | K5: North | L5: Premium | M5: 45114 | N5: 179.97
A6: TRX0212 | B6: 45400 | C6: CUST003 | D6: Michael Brown | E6: P008 | F6: Bookshelf | G6: Furniture | H6: 5 | I6: 149.99 | J6: Credit Card | K6: North | L6: Premium | M6: 45295 | N6: 749.95
A7: TRX0092 | B7: 45403 | C7: CUST024 | D7: Dorothy Nelson | E7: P005 | F7: Blender | G7: Appliances | H7: 2 | I7: 59.99 | J7: Cash | K7: West | L7: Standard | M7: 44746 | N7: 119.98
A8: TRX0193 | B8: 45403 | C8: CUST024 | D8: Dorothy Nelson | E8: P003 | F8: Headphones | G8: Electronics | H8: 5 | I8: 149.99 | J8: Credit Card | K8: Central | L8: Standard | M8: 44418 | N8: 749.95
A9: TRX0240 | B9: 45403 | C9: CUST017 | D9: Charles Allen | E9: P005 | F9: Blender | G9: Appliances | H9: 3 | I9: 59.99 | J9: Debit Card | K9: South | L9: Basic | M9: 45007 | N9: 179.97
A10: TRX0135 | B10: 45405 | C10: CUST009 | D10: Robert Thomas | E10: P001 | F10: Laptop | G10: Electronics | H10: 3 | I10: 899.99 | J10: PayPal | K10: East | L10: Standard | M10: 45299 | N10: 2699.97
A11: TRX0185 | B11: 45408 | C11: CUST026 | D11: Karen Hill | E11: P005 | F11: Blender | G11: Appliances | H11: 3 | I11: 59.99 | J11: Cash | K11: West | L11: Premium | M11: 45207 | N11: 179.97
A12: TRX0138 | B12: 45408 | C12: CUST022 | D12: Susan Green | E12: P008 | F12: Bookshelf | G12: Furniture | H12: 1 | I12: 149.99 | J12: Credit Card | K12: West | L12: Standard | M12: 45103 | N12: 149.99
A13: TRX0209 | B13: 45408 | C13: CUST046 | D13: Kathleen Bennett | E13: P008 | F13: Bookshelf | G13: Furniture | H13: 5 | I13: 149.99 | J13: Debit Card | K13: North | L13: Basic | M13: 44830 | N13: 749.95
... A251: TRX0064 | B251: 45758 | C251: CUST031 | D251: Steven Turner | E251: P010 | F251: Keyboard | G251: Electronics | H251: 3 | I251: 89.99 | J251: Debit Card | K251: North | L251: Premium | M251: 44878 | N251: 269.97

Sheet What if 
A1: Quantity | B1: Unit_Price | C1: Total_Amount | D1: sum of total amount | F1: Scenario Summary | L1: Goal seek | M1: Column1 | N1: Column2
A2: 1 | B2: 249.99 | C2: =A2*B2 -> 249.99 | D2: =SUM(C2:C10) -> 11909.55 | H2: Current Values: | I2: incrise | J2: dicrise | L2: Quantity | M2: Total_Amount | N2: Unit_Price
A3: 2 | B3: 249.99 | C3: =A3*B3 -> 499.98 | I3: Created by Hanee on 09-11-2025 | J3: Created by Hanee on 09-11-2025 | L3: 3 | M3: =L3*N3 -> 300 | N3: 100
A4: 3 | B4: 59.99 | C4: =A4*B4 -> 179.97 | F4: Changing Cells: | L4: 4 | M4: =L4*N4 -> 400 | N4: 100
A5: 4 | B5: 59.99 | C5: =A5*B5 -> 239.96 | G5: $A$2 | H5: 1 | I5: 1 | J5: 9 | L5: 5 | M5: =L5*N5 -> 500 | N5: 100
A6: 5 | B6: 149.99 | C6: =A6*B6 -> 749.95 | G6: $A$3 | H6: 2 | I6: 2 | J6: 8 | L6: 6 | M6: =L6*N6 -> 600 | N6: 100
A7: 6 | B7: 59.99 | C7: =A7*B7 -> 359.94 | G7: $A$4 | H7: 3 | I7: 3 | J7: 7 | L7: 7 | M7: =L7*N7 -> 700 | N7: 100
A8: 7 | B8: 149.99 | C8: =A8*B8 -> 1049.93 | G8: $A$5 | H8: 4 | I8: 4 | J8: 6 | L8: 10 | M8: =L8*N8 -> 800 | N8: 80
A9: 8 | B9: 59.99 | C9: =A9*B9 -> 479.92 | G9: $A$6 | H9: 5 | I9: 5 | J9: 5 | L9: 2 | M9: =L9*N9 -> 900 | N9: 450
A10: 9 | B10: 899.99 | C10: =A10*B10 -> 8099.91 | G10: $A$7 | H10: 6 | I10: 6 | J10: 4 | L10: 4 | M10: =L10*N10 -> 100 | N10: 25
G11: $A$8 | H11: 7 | I11: 7 | J11: 3 | L11: 21 | M11: =L11*N11 -> 200 | N11: 9.5238095
G12: $A$9 | H12: 8 | I12: 8 | J12: 2
G13: $A$10 | H13: 9 | I13: 9 | J13: 1
F14: Result Cells:
G15: $D$2 | H15: 11909.55 | I15: 11909.55 | J15: 7489.55
K18: s

Sheet liniar reggretion
A1: Unit_Price | B1: Unit_Price | C1: Total_Amount | F1: mean X | G1: mean Y | H1: diff of X | I1: diff of Y | J1: Product of Difference | K1: Sum of Product Difference of X and Y | L1: Difference of X Square | M1: Sum of Square Difference of X | N1: m | O1: c | Q1: LR
A2: 249.99 | B2: 249.99 | C2: 749.97 | F2: =AVERAGE(B2:B243) -> 295.15529 | G2: =AVERAGE(C2:C243) -> 917.49033 | H2: =B2-$F$2 -> -45.165289 | I2: =C2-$G$2 -> -167.52033 | J2: =H2*I2 -> 7566.1042 | K2: =AVERAGE(J2:J243) -> 233568.78 | L2: =H2*H2 -> 2039.9034 | M2: =AVERAGE(L2:L243) -> 73964.642 | N2: =K2/M2 -> 3.1578437 | O2: =G2-(N2*F2) -> -14.563952 | P2: =C244-D244 -> -89.630406 | Q2: =1-P2/C244 -> 1.498002
A3: 249.99 | B3: 249.99 | C3: 749.97 | H3: =B3-$F$2 -> -45.165289 | I3: =C3-$G$2 -> -167.52033 | J3: =H3*I3 -> 7566.1042 | L3: =H3*H3 -> 2039.9034 | P3: =C245-D245 -> -795.91509 | Q3: =1-P3/C245 -> 1.5685189
A4: 59.99 | B4: 59.99 | C4: 179.97 | H4: =B4-$F$2 -> -235.16529 | I4: =C4-$G$2 -> -737.52033 | J4: =H4*I4 -> 173439.18 | L4: =H4*H4 -> 55302.713 | P4: =C246-D246 -> -127.49384 | Q4: =1-P4/C246 -> 1.0472205
A5: 59.99 | B5: 59.99 | C5: 179.97 | H5: =B5-$F$2 -> -235.16529 | I5: =C5-$G$2 -> -737.52033 | J5: =H5*I5 -> 173439.18 | L5: =H5*H5 -> 55302.713 | P5: =C247-D247 -> 1.9380316 | Q5: =1-P5/C247 -> 0.99192386
A6: 149.99 | B6: 149.99 | C6: 749.95 | H6: =B6-$F$2 -> -145.16529 | I6: =C6-$G$2 -> -167.54033 | J6: =H6*I6 -> 24321.041 | L6: =H6*H6 -> 21072.961 | P6: =C248-D248 -> -179.62041 | Q6: =1-P6/C248 -> 2.9960041
A7: 59.99 | B7: 59.99 | C7: 119.98 | H7: =B7-$F$2 -> -235.16529 | I7: =C7-$G$2 -> -797.51033 | J7: =H7*I7 -> 187546.75 | L7: =H7*H7 -> 55302.713 | P7: =C249-D249 -> -95.925088 | Q7: =1-P7/C249 -> 1.0456793
A8: 149.99 | B8: 149.99 | C8: 749.95 | H8: =B8-$F$2 -> -145.16529 | I8: =C8-$G$2 -> -167.54033 | J8: =H8*I8 -> 24321.041 | L8: =H8*H8 -> 21072.961 | P8: =C250-D250 -> -89.630406 | Q8: =1-P8/C250 -> 1.498002
A9: 59.99 | B9: 59.99 | C9: 179.97 | H9: =B9-$F$2 -> -235.16529 | I9: =C9-$G$2 -> -737.52033 | J9: =H9*I9 -> 173439.18 | L9: =H9*H9 -> 55302.713 | P9: =C251-D251 -> 0.35959414 | Q9: =1-P9/C251 -> 0.99866802
A10: 899.99 | B10: 899.99 | C10: 2699.97 | H10: =B10-$F$2 -> 604.83471 | I10: =C10-$G$2 -> 1782.4797 | J10: =H10*I10 -> 1078105.6 | L10: =H10*H10 -> 365825.03 | Q10: =AVERAGE(Q2:Q9) -> 1.4555023
A11: 59.99 | B11: 59.99 | C11: 179.97 | H11: =B11-$F$2 -> -235.16529 | I11: =C11-$G$2 -> -737.52033 | J11: =H11*I11 -> 173439.18 | L11: =H11*H11 -> 55302.713
A12: 149.99 | B12: 149.99 | C12: 149.99 | H12: =B12-$F$2 -> -145.16529 | I12: =C12-$G$2 -> -767.50033 | J12: =H12*I12 -> 111414.41 | L12: =H12*H12 -> 21072.961
A13: 149.99 | B13: 149.99 | C13: 749.95 | H13: =B13-$F$2 -> -145.16529 | I13: =C13-$G$2 -> -167.54033 | J13: =H13*I13 -> 24321.041 | L13: =H13*H13 -> 21072.961
A14: 149.99 | B14: 149.99 | C14: 449.97 | H14: =B14-$F$2 -> -145.16529 | I14: =C14-$G$2 -> -467.52033 | J14: =H14*I14 -> 67867.724 | L14: =H14*H14 -> 21072.961
A15: 59.99 | B15: 59.99 | C15: 179.97 | H15: =B15-$F$2 -> -235.16529 | I15: =C15-$G$2 -> -737.52033 | J15: =H15*I15 -> 173439.18 | L15: =H15*H15 -> 55302.713
A16: 699.99 | B16: 699.99 | C16: 2099.97 | H16: =B16-$F$2 -> 404.83471 | I16: =C16-$G$2 -> 1182.4797 | J16: =H16*I16 -> 478708.81 | L16: =H16*H16 -> 163891.14
A17: 899.99 | B17: 899.99 | C17: 899.99 | H17: =B17-$F$2 -> 604.83471 | I17: =C17-$G$2 -> -17.500331 | J17: =H17*I17 -> -10584.807 | L17: =H17*H17 -> 365825.03
A18: 149.99 | B18: 149.99 | C18: 599.96 | H18: =B18-$F$2 -> -145.16529 | I18: =C18-$G$2 -> -317.53033 | J18: =H18*I18 -> 46094.382 | L18: =H18*H18 -> 21072.961
A19: 699.99 | B19: 699.99 | C19: 1399.98 | H19: =B19-$F$2 -> 404.83471 | I19: =C19-$G$2 -> 482.48967 | J19: =H19*I19 -> 195328.57 | L19: =H19*H19 -> 163891.14
A20: 899.99 | B20: 899.99 | C20: 3599.96 | H20: =B20-$F$2 -> 604.83471 | I20: =C20-$G$2 -> 2682.4697 | J20: =H20*I20 -> 1622450.8 | L20: =H20*H20 -> 365825.03
A21: 249.99 | B21: 249.99 | C21: 749.97 | H21: =B21-$F$2 -> -45.165289 | I21: =C21-$G$2 -> -167.52033 | J21: =H21*I21 -> 7566.1042 | L21: =H21*H21 -> 2039.9034
A22: 699.99 | B22: 699.99 | C22: 3499.95 | H22: =B22-$F$2 -> 404.83471 | I22: =C22-$G$2 -> 2582.4597 | J22: =H22*I22 -> 1045469.3 | L22: =H22*H22 -> 163891.14
... A243: 149.99 | B243: 149.99 | C243: 449.97 | H243: =B243-$F$2 -> -145.16529 | I243: =C243-$G$2 -> -467.52033 | J243: =H243*I243 -> 67867.724 | L243: =H243*H243 -> 21072.961
A244: 89.99 | C244: 179.98 | D244: =$N$2*A244+$O$2 -> 269.61041
A245: 699.99 | C245: 1399.98 | D245: =$N$2*A245+$O$2 -> 2195.8951
A246: 899.99 | C246: 2699.97 | D246: =$N$2*A246+$O$2 -> 2827.4638
A247: 79.99 | C247: 239.97 | D247: =$N$2*A247+$O$2 -> 238.03197
A248: 89.99 | C248: 89.99 | D248: =$N$2*A248+$O$2 -> 269.61041
A249: 699.99 | C249: 2099.97 | D249: =$N$2*A249+$O$2 -> 2195.8951
A250: 89.99 | C250: 179.98 | D250: =$N$2*A250+$O$2 -> 269.61041
A251: 89.99 | C251: 269.97 | D251: =$N$2*A251+$O$2 -> 269.61041
